pera_transcript
