Metadata-Version: 2.1
Name: pera-transcript
Version: 0.2.0
Summary: A tool to generate the unofficial transcript automatically for undergraduate students at University of Peradeniya.
Home-page: https://github.com/sathiiii/pera-transcript
Author: Sathira Silva
Author-email: sathirasofte@gmail.com
License: MIT License
Classifier: Development Status :: 5 - Production/Stable
Classifier: Intended Audience :: Science/Research
Classifier: License :: OSI Approved :: MIT License
Classifier: Operating System :: POSIX :: Linux
Classifier: Programming Language :: Python :: 2
Classifier: Programming Language :: Python :: 2.7
Classifier: Programming Language :: Python :: 3
Classifier: Programming Language :: Python :: 3.4
Classifier: Programming Language :: Python :: 3.5
Classifier: Programming Language :: Python :: 3.8
Classifier: Programming Language :: Python :: 3.9
Classifier: Programming Language :: Python :: 3.10
License-File: LICENSE
